dddd_utils/__init__.py
dddd_utils/apollo.py
dddd_utils/basespider.py
dddd_utils/basespider_selenium.py
dddd_utils/ftp.py
dddd_utils/logger.py
dddd_utils/mail.py
dddd_utils/mysql.py
dddd_utils/retry.py
dddd_utils-1.1.15.dist-info/LICENSE
dddd_utils-1.1.15.dist-info/METADATA
dddd_utils-1.1.15.dist-info/WHEEL
dddd_utils-1.1.15.dist-info/top_level.txt
dddd_utils-1.1.15.dist-info/RECORD
