Metadata-Version: 2.1
Name: dddd-utils
Version: 1.1.15
Summary: 带带弟弟小工具
Home-page: https://gitee.com/duquan1995/dq-utils
Author: MyYasuo666
Author-email: author@example.com
License: UNKNOWN
Project-URL: Bug Tracker, https://github.com/pypa/sampleproject/issues
Platform: UNKNOWN
Classifier: Programming Language :: Python :: 3
Classifier: License :: OSI Approved :: MIT License
Classifier: Operating System :: OS Independent
Requires-Python: >=3.6
License-File: LICENSE
Requires-Dist: premailer (>=3.1.0)
